zope.exceptions-5.2-py3.11-nspkg.pth
zope/exceptions/__init__.py
zope/exceptions/exceptionformatter.py
zope/exceptions/interfaces.py
zope/exceptions/log.py
zope/exceptions/tests/__init__.py
zope/exceptions/tests/test_exceptionformatter.py
zope/exceptions/tests/test_log.py
zope.exceptions-5.2.dist-info/LICENSE.txt
zope.exceptions-5.2.dist-info/METADATA
zope.exceptions-5.2.dist-info/WHEEL
zope.exceptions-5.2.dist-info/namespace_packages.txt
zope.exceptions-5.2.dist-info/top_level.txt
zope.exceptions-5.2.dist-info/RECORD
